support/__init__.py
support/dialogs/__init__.py
support/dialogs/api.py
support/dialogs/create_ticket/__init__.py
support/dialogs/create_ticket/confirm.py
support/dialogs/create_ticket/enter_text.py
support/dialogs/create_ticket/enter_title.py
support/dialogs/states.py
support/dialogs/support/__init__.py
support/dialogs/support/close_tickets.py
support/dialogs/support/main.py
support/dialogs/support/open_tickets.py
support/dialogs/support/ticket_details.py
support/dialogs/support/utils.py
support/settings.py
support/utils.py
chatlabs_aiogram_support-0.2.0.dist-info/METADATA
chatlabs_aiogram_support-0.2.0.dist-info/WHEEL
chatlabs_aiogram_support-0.2.0.dist-info/RECORD
