Metadata-Version: 2.4
Name: chatlabs-aiogram-support
Version: 0.2.0
Summary: 
Author: Rostislaww
Author-email: rostiki.com@mail.ru
Requires-Python: >=3.11,<4.0
Classifier: Programming Language :: Python :: 3
Classifier: Programming Language :: Python :: 3.11
Classifier: Programming Language :: Python :: 3.12
Classifier: Programming Language :: Python :: 3.13
Classifier: Programming Language :: Python :: 3.14
Requires-Dist: aiogram (>=3.14.0,<4.0.0)
Requires-Dist: aiogram-dialog (>=2.3.1,<3.0.0)
Project-URL: Homepage, https://github.com/RostHarcha/chatlabs-aiogram-support
